LICENSE.txt
README.md
setup.cfg
setup.py
EyesLibrary/__init__.py
EyesLibrary/version.py
EyesLibrary/keywords/__init__.py
EyesLibrary/keywords/check.py
EyesLibrary/keywords/session.py
EyesLibrary/keywords/target.py
EyesLibrary/resources/__init__.py
EyesLibrary/resources/utils.py
EyesLibrary/resources/variables.py
robotframework_eyeslibrarysel3.egg-info/PKG-INFO
robotframework_eyeslibrarysel3.egg-info/SOURCES.txt
robotframework_eyeslibrarysel3.egg-info/dependency_links.txt
robotframework_eyeslibrarysel3.egg-info/requires.txt
robotframework_eyeslibrarysel3.egg-info/top_level.txt