Metadata-Version: 2.1
Name: robotframework-eyeslibrarysel3
Version: 2.2
Summary: Visual verification testing library for Robot Framework
Home-page: UNKNOWN
Author: Chris Hunter
Author-email: <hunter.james.chris@gmail.com>
License: Apache License 2.0
Download-URL: https://github.com/chunter4/EyesLibrary/archive/v2.2.tar.gz
Keywords: robotframework testing testautomation eyes-selenium selenium appium visual-verification
Platform: any
Classifier: License :: OSI Approved :: Apache Software License
Classifier: Programming Language :: Python :: 2.7
Classifier: Programming Language :: Python :: 3.6
Classifier: Development Status :: 5 - Production/Stable
Classifier: Intended Audience :: Developers
Classifier: Framework :: Robot Framework :: Library
Classifier: Topic :: Software Development :: Testing
Classifier: Topic :: Software Development :: Quality Assurance
